CHANGES.rst
DESCRIPTION.rst
MANIFEST
MANIFEST.in
README.md
setup.cfg
setup.py
cygenja/__init__.py
cygenja/generator.py
cygenja.egg-info/PKG-INFO
cygenja.egg-info/SOURCES.txt
cygenja.egg-info/dependency_links.txt
cygenja.egg-info/pbr.json
cygenja.egg-info/requires.txt
cygenja.egg-info/top_level.txt
cygenja/filters/__init__.py
cygenja/filters/type_filters.py
cygenja/helpers/__init__.py
cygenja/helpers/file_helpers.py
cygenja/helpers/version.py
cygenja/treemap/__init__.py
cygenja/treemap/location_descriptor.py
cygenja/treemap/treemap.py
cygenja/treemap/treemap_node.py
doc/Makefile
doc/build/doctrees/contents.doctree
doc/build/doctrees/environment.pickle
doc/build/doctrees/examples.doctree
doc/build/doctrees/installation.doctree
doc/build/doctrees/introduction.doctree
doc/build/doctrees/usage.doctree
doc/build/doctrees/use.doctree
doc/build/html/.buildinfo
doc/build/html/contents.html
doc/build/html/examples.html
doc/build/html/genindex.html
doc/build/html/installation.html
doc/build/html/introduction.html
doc/build/html/objects.inv
doc/build/html/search.html
doc/build/html/searchindex.js
doc/build/html/usage.html
doc/build/html/use.html
doc/build/html/_sources/contents.txt
doc/build/html/_sources/examples.txt
doc/build/html/_sources/installation.txt
doc/build/html/_sources/introduction.txt
doc/build/html/_sources/usage.txt
doc/build/html/_sources/use.txt
doc/build/html/_static/ajax-loader.gif
doc/build/html/_static/basic.css
doc/build/html/_static/bootstrap-sphinx.css
doc/build/html/_static/bootstrap-sphinx.js
doc/build/html/_static/comment-bright.png
doc/build/html/_static/comment-close.png
doc/build/html/_static/comment.png
doc/build/html/_static/doctools.js
doc/build/html/_static/down-pressed.png
doc/build/html/_static/down.png
doc/build/html/_static/file.png
doc/build/html/_static/jquery-1.11.1.js
doc/build/html/_static/jquery.js
doc/build/html/_static/minus.png
doc/build/html/_static/plus.png
doc/build/html/_static/pygments.css
doc/build/html/_static/searchtools.js
doc/build/html/_static/underscore-1.3.1.js
doc/build/html/_static/underscore.js
doc/build/html/_static/up-pressed.png
doc/build/html/_static/up.png
