Metadata-Version: 1.1
Name: cygenja
Version: 0.5.2
Summary: Cython code generator with Jinja2
Home-page: https://github.com/PythonOptimizers/cygenja
Author: Nikolaj van Omme
Author-email: nikolaj@funartech.com
License: LGPL
Download-URL: https://github.com/PythonOptimizers/cygenja
Platform: UNKNOWN
Classifier: Development Status :: 4 - Beta
Classifier: Intended Audience :: Science/Research
Classifier: Intended Audience :: Developers
Classifier: License :: OSI Approved
Classifier: Programming Language :: Python
Classifier: Topic :: Software Development
Classifier: Topic :: Scientific/Engineering
Classifier: Operating System :: POSIX
Classifier: Operating System :: Unix
Classifier: Operating System :: MacOS :: MacOS X
Classifier: Natural Language :: English
